gaussufunc.cpython-311-x86_64-linux-gnu.so
beamfit/__init__.py
beamfit/debug.py
beamfit/factory.py
beamfit/fit_param_conversion.py
beamfit/gaussian_fit_1d.py
beamfit/gaussian_linear_least_squares.py
beamfit/plotting_and_output.py
beamfit/rms_integration.py
beamfit/sigma_transformations.py
beamfit/supergaussian.py
beamfit/supergaussian_c_drivers.py
beamfit/utils.py
src/gaussian.c
tests/test_analysis.py
tests/test_fitting.py
tests/test_sigma_parameterization.py
beamfit-1.13.dist-info/METADATA
beamfit-1.13.dist-info/WHEEL
beamfit-1.13.dist-info/top_level.txt
beamfit-1.13.dist-info/RECORD
beamfit-1.13.dist-info/licenses/LICENSE
