Metadata-Version: 2.4
Name: beamfit
Version: 1.13
Summary: Robust laser and charged particle beam image analysis
Author-email: "Christopher M. Pierce" <contact@chris-pierce.com>
License: BSD 3-Clause License
Project-URL: Homepage, https://github.com/electronsandstuff/Beamfit
Project-URL: Repository, https://github.com/electronsandstuff/Beamfit
Classifier: Programming Language :: Python :: 3
Classifier: License :: OSI Approved :: BSD License
Classifier: Development Status :: 4 - Beta
Classifier: Operating System :: OS Independent
Requires-Python: >=3.9
License-File: LICENSE
Requires-Dist: numpy
Requires-Dist: matplotlib
Requires-Dist: scipy
Dynamic: license-file
